pyETT/__init__.py
pyETT/ett.py
pyETT/ett_parser.py
pyETT/setup.py
pyETT-0.2.6.dist-info/LICENSE.md
pyETT-0.2.6.dist-info/METADATA
pyETT-0.2.6.dist-info/WHEEL
pyETT-0.2.6.dist-info/top_level.txt
pyETT-0.2.6.dist-info/RECORD
