Metadata-Version: 2.1
Name: pyETT
Version: 0.2.6
Summary: Python library for Eleven VR Table Tennis data
Home-page: https://pyett.readthedocs.io/
Author: Tharsis T. P. Souza
License: The content of this repository is licensed under the Creative Commons Attribution-NonCommercial-ShareAlike 4.0 International License. To view a copy of this license, visit https://creativecommons.org/licenses/by-nc-sa/4.0/ or send a letter to Creative Commons, 444 Castro Street, Suite 900, Mountain View, California, 94041, USA.        
Platform: UNKNOWN
License-File: LICENSE.md
Requires-Dist: requests (==2.22.0)
Requires-Dist: pandas (==1.3.0)
Requires-Dist: nbsphinx (==0.8.6)
Requires-Dist: aiohttp (==3.6.2)
Requires-Dist: lxml
Requires-Dist: pandas-stubs (==1.1.0.12)
Requires-Dist: nest-asyncio (==1.5.1)
